pvpower/estimator.py
pvpower/forecast.py
pvpower/forecast_24h.py
pvpower/mosmix.py
pvpower/refreshing_estimator.py
pvpower/traindata.py
pvpower/trainingcenter.py
pvpower/weather_forecast.py
pvpower-0.3.16.dist-info/LICENSE
pvpower-0.3.16.dist-info/METADATA
pvpower-0.3.16.dist-info/WHEEL
pvpower-0.3.16.dist-info/top_level.txt
pvpower-0.3.16.dist-info/RECORD
