Metadata-Version: 2.1
Name: pvpower
Version: 0.3.16
Summary: photovoltaic, forecast, power, solar, PV, weather, DWD, machine learning, energy management
Author: Gregor Roth
Author-email: gregor.roth@web.de
Requires-Python: >=3.8
License-File: LICENSE
Requires-Dist: scikit-learn (==1.1.2)
Requires-Dist: appdirs (==1.4.4)
Requires-Dist: stream-unzip (==0.0.70)
Requires-Dist: httpx (==0.23.0)
Requires-Dist: pytz (==2022.5)
